beancount_cc_importers-0.1.14.dist-info/METADATA
beancount_cc_importers-0.1.14.dist-info/WHEEL
beancount_cc_importers-0.1.14.dist-info/entry_points.txt
beancount_cc_importers-0.1.14.dist-info/licenses/LICENSE
beancount_cc_importers/__init__.py
beancount_cc_importers/alipay.py
beancount_cc_importers/cmb.py
beancount_cc_importers/comm_loan.py
beancount_cc_importers/eml.py
beancount_cc_importers/lingqian.py
beancount_cc_importers/mssalary.py
beancount_cc_importers/util/__init__.py
beancount_cc_importers/util/eml2csv.py
beancount_cc_importers-0.1.14.dist-info/RECORD
