Metadata-Version: 2.1
Name: beancount_cc_importers
Version: 0.1.14
Summary: Beancount importer plugin
Author-Email: Chao Chen <wenbushi@gmail.com>
License: GPL-3.0-or-later
Requires-Python: >=3.9
Requires-Dist: lxml>=4.9.3
Requires-Dist: beancount>=2.3.6
Requires-Dist: python-dateutil>=2.9.0.post0
Requires-Dist: beangulp>=0.1.1
